pydingo/__init__.py
pydingo/client.py
pydingo/client_stub.py
pydingo-0.1.dist-info/METADATA
pydingo-0.1.dist-info/WHEEL
pydingo-0.1.dist-info/top_level.txt
pydingo-0.1.dist-info/RECORD
