Metadata-Version: 2.1
Name: pydingo
Version: 0.1
Summary: holography library
Home-page: UNKNOWN
Author: See-Through Scientific
Author-email: UNKNOWN
License: UNKNOWN
Platform: UNKNOWN
